visionkernel/__init__.py
visionkernel/base.py
visionkernel-0.0.1.dist-info/LICENSE
visionkernel-0.0.1.dist-info/METADATA
visionkernel-0.0.1.dist-info/WHEEL
visionkernel-0.0.1.dist-info/top_level.txt
visionkernel-0.0.1.dist-info/RECORD
