Metadata-Version: 2.1
Name: visionkernel
Version: 0.0.1
Summary: ...
Author: Yavuz Selim Inan
Author-email: <yinan4099@gmail.com>
Keywords: python,image,feature extraction,image filter,imaage process,augmentation
Classifier: Development Status :: 1 - Planning
Classifier: Intended Audience :: Developers
Classifier: Programming Language :: Python :: 3
Classifier: Operating System :: Unix
Classifier: Operating System :: MacOS :: MacOS X
Classifier: Operating System :: Microsoft :: Windows
License-File: LICENSE
Requires-Dist: opencv-python
